autopip/__init__.py
autopip/constants.py
autopip/crontab.py
autopip/exceptions.py
autopip/inspect_app.py
autopip/manager.py
autopip/utils.py
autopip/embedded/README.rst
autopip-1.7.8.dist-info/LICENSE
autopip-1.7.8.dist-info/METADATA
autopip-1.7.8.dist-info/WHEEL
autopip-1.7.8.dist-info/entry_points.txt
autopip-1.7.8.dist-info/top_level.txt
autopip-1.7.8.dist-info/RECORD
