Metadata-Version: 2.1
Name: autopip
Version: 1.7.8
Summary: Easily install apps from PyPI and automatically keep them updated
Home-page: https://github.com/maxzheng/autopip
Author: Max Zheng
Author-email: maxzheng.os@gmail.com
License: MIT
Keywords: automatically pip virtualenv auto-update apps
Classifier: Development Status :: 5 - Production/Stable
Classifier: Intended Audience :: Developers
Classifier: Topic :: Software Development :: Build Tools
Classifier: License :: OSI Approved :: MIT License
Classifier: Programming Language :: Python :: 3
Classifier: Programming Language :: Python :: 3.6
Requires-Python: >=3.6
License-File: LICENSE
